alph_sdk/__init__.py
alph_sdk/_version.py
alph_sdk/auth.py
alph_sdk/basesdk.py
alph_sdk/httpclient.py
alph_sdk/orgs.py
alph_sdk/projects.py
alph_sdk/py.typed
alph_sdk/sdk.py
alph_sdk/sdkconfiguration.py
alph_sdk/tunnels.py
alph_sdk/user_sdk.py
alph_sdk/_hooks/__init__.py
alph_sdk/_hooks/sdkhooks.py
alph_sdk/_hooks/types.py
alph_sdk/errors/__init__.py
alph_sdk/errors/alphsdkerror.py
alph_sdk/errors/apierror.py
alph_sdk/errors/no_response_error.py
alph_sdk/errors/responsevalidationerror.py
alph_sdk/models/__init__.py
alph_sdk/models/cliauthop.py
alph_sdk/models/createorgop.py
alph_sdk/models/createprojectop.py
alph_sdk/models/createtunnelop.py
alph_sdk/models/deleteprojectop.py
alph_sdk/models/deletetunnelop.py
alph_sdk/models/getorgsop.py
alph_sdk/models/getprojectsop.py
alph_sdk/models/getprojectstatusop.py
alph_sdk/models/gettunnelop.py
alph_sdk/models/getuserinfoop.py
alph_sdk/models/security.py
alph_sdk/models/startprojectop.py
alph_sdk/models/stopprojectop.py
alph_sdk/types/__init__.py
alph_sdk/types/basemodel.py
alph_sdk/utils/__init__.py
alph_sdk/utils/annotations.py
alph_sdk/utils/datetimes.py
alph_sdk/utils/enums.py
alph_sdk/utils/eventstreaming.py
alph_sdk/utils/forms.py
alph_sdk/utils/headers.py
alph_sdk/utils/logger.py
alph_sdk/utils/metadata.py
alph_sdk/utils/queryparams.py
alph_sdk/utils/requestbodies.py
alph_sdk/utils/retries.py
alph_sdk/utils/security.py
alph_sdk/utils/serializers.py
alph_sdk/utils/unmarshal_json_response.py
alph_sdk/utils/url.py
alph_sdk/utils/values.py
alph_sdk-0.5.2.dist-info/METADATA
alph_sdk-0.5.2.dist-info/WHEEL
alph_sdk-0.5.2.dist-info/top_level.txt
alph_sdk-0.5.2.dist-info/RECORD
