Metadata-Version: 2.4
Name: alph-sdk
Version: 0.5.2
Summary: Python Client SDK Generated by Speakeasy.
Author: Speakeasy
Project-URL: repository, https://github.com/americandatascience/alph-python-sdk.git
Requires-Python: >=3.9.2
Requires-Dist: httpcore>=1.0.9
Requires-Dist: httpx>=0.28.1
Requires-Dist: pydantic>=2.11.2
